<?xml version="1.0" encoding="utf-8" ?>
<odoo>
    <record id="view_stock_kardex_report" model="ir.ui.view">
        <field name="name">Inventory Kardex Report</field>
        <field name="model">report.kardex.report.wiz</field>
        <field name="arch" type="xml">
            <form>
                <group>
                    <group>
                        <field name="date_from" />
                        <field name="date_to" />
                    </group>
                </group>
                <footer>
                    <button name="open_table" string="CONFIRM" type="object" class="btn-primary" />
                    <button string="Cancel" class="btn-secondary" special="cancel" />
                </footer>
            </form>
        </field>
    </record>

    <record id="action_stock_kardex_report" model="ir.actions.act_window">
        <field name="name">inventory Kardex Report</field>
        <field name="res_model">report.kardex.report.wiz</field>
        <field name="view_mode">form</field>
        <field name="view_id" ref="view_stock_kardex_report" />
        <field name="target">new</field>
    </record>

    <menuitem
        id="menu_movs_report"
        name="Kardex Analysis"
        parent="quant_reports_menu"
        action="action_stock_kardex_report"
    />

</odoo>
